setup.py
mess_server_leget.egg-info/PKG-INFO
mess_server_leget.egg-info/SOURCES.txt
mess_server_leget.egg-info/dependency_links.txt
mess_server_leget.egg-info/requires.txt
mess_server_leget.egg-info/top_level.txt
server/__init__.py
server/server.py
server/common/__init__.py
server/common/deccor_log.py
server/common/descryptors.py
server/common/errors.py
server/common/metaclasses.py
server/common/settings.py
server/common/utils.py
server/log/__init__.py
server/log/client_log_conf.py
server/log/server_log_conf.py
server/log/logs/__init__.py
server/server/__init__.py
server/server/add_user.py
server/server/config_window.py
server/server/core.py
server/server/db_server.py
server/server/main_window.py
server/server/remove_user.py
server/server/stat_window.py
server/unit_test/__init__.py
server/unit_test/test_client.py
server/unit_test/test_server.py
server/unit_test/test_utils.py